wenchang/__init__.py
wenchang/base/__init__.py
wenchang/base/node.py
wenchang/base/nodetype.py
wenchang/base/tests/__init__.py
wenchang/base/tests/test_class_node.py
wenchang/base/tests/test_class_nodetype.py
wenchang/resource/__init__.py
wenchang/resource/python/__init__.py
wenchang/resource/python/pyargument.py
wenchang/resource/python/pyclass.py
wenchang/resource/python/pycomment.py
wenchang/resource/python/pyfunction.py
wenchang/resource/python/pyimport.py
wenchang/resource/python/pymodule.py
wenchang/resource/python/pynode.py
wenchang/resource/python/pystatement.py
wenchang/resource/python/tests/__init__.py
wenchang/resource/python/tests/sample.py
wenchang/resource/python/tests/test_class_pyargument.py
wenchang/resource/python/tests/test_class_pyclass.py
wenchang/resource/python/tests/test_class_pycomment.py
wenchang/resource/python/tests/test_class_pyfunction.py
wenchang/resource/python/tests/test_class_pyimport.py
wenchang/resource/python/tests/test_class_pymodule.py
wenchang/resource/python/tests/test_class_pynode.py
wenchang/resource/python/tests/test_class_pystatement.py
x17_wenchang-0.1.0.dist-info/METADATA
x17_wenchang-0.1.0.dist-info/WHEEL
x17_wenchang-0.1.0.dist-info/top_level.txt
x17_wenchang-0.1.0.dist-info/RECORD
