Metadata-Version: 2.4
Name: x17-wenchang
Version: 0.1.0
Summary: A semantic AST-based documentation engine for Python, inspired by 文昌帝君.
Author-email: Xing Xing <x.xing.work@gmail.com>
License: MIT
Project-URL: Homepage, https://github.com/Xing-Xing-1/x17/tree/main/x17-wenchang
Project-URL: Repository, https://github.com/Xing-Xing-1/x17
Project-URL: Documentation, https://pypi.org/project/x17-wenchang/
Requires-Python: >=3.8
Requires-Dist: x17-pangu
